helloSOS/__init__.py
helloSOS/exact_code_strings.py
helloSOS/exact_prac1.py
helloSOS/exact_prac3.py
helloSOS/exact_prac4.py
helloSOS/exact_prac5.py
helloSOS/exact_prac7.py
helloSOS/exact_prac8.py
helloSOS/rpa_code_strings.py
helloSOS/updated_kiras_init.py
hellosos-0.1.0.dist-info/licenses/LICENSE
hellosos-0.1.0.dist-info/METADATA
hellosos-0.1.0.dist-info/WHEEL
hellosos-0.1.0.dist-info/top_level.txt
hellosos-0.1.0.dist-info/RECORD
